lightly_mundig-0.1.9.dist-info/METADATA
lightly_mundig-0.1.9.dist-info/WHEEL
lightly_mundig-0.1.9.dist-info/licenses/LICENSE.md
lightly_mundig/__init__.py
lightly_mundig/lightly_mundig.abi3.so
lightly_mundig-0.1.9.dist-info/RECORD
