Metadata-Version: 2.4
Name: lightly-mundig
Version: 0.1.9
Classifier: Development Status :: 4 - Beta
Classifier: Intended Audience :: Developers
Classifier: License :: OSI Approved :: MIT License
Classifier: Programming Language :: Python :: 3
Classifier: Programming Language :: Python :: 3.8
Classifier: Programming Language :: Python :: 3.9
Classifier: Programming Language :: Python :: 3.10
Classifier: Programming Language :: Python :: 3.11
Classifier: Programming Language :: Python :: 3.12
Classifier: Programming Language :: Rust
Requires-Dist: pyjwt[crypto]>=2.9 ; extra == 'dev'
Requires-Dist: pytest>=6.0 ; extra == 'dev'
Requires-Dist: maturin>=1.0,<2.0 ; extra == 'dev'
Requires-Dist: ruff-lsp ; extra == 'lsp'
Requires-Dist: pylsp-mypy ; extra == 'lsp'
Provides-Extra: dev
Provides-Extra: lsp
License-File: LICENSE.md
Summary: Python bindings for selection
Author: Lightly Inc.
Author-email: team@lightly.ai
License: MIT
Requires-Python: >=3.8
